micvbang/__init__.py
micvbang/dictutil.py
micvbang/io.py
micvbang/jsonutil.py
micvbang/progress.py
micvbang/randutil.py
micvbang/version.py
micvbang-0.0.14.dist-info/METADATA
micvbang-0.0.14.dist-info/RECORD
micvbang-0.0.14.dist-info/WHEEL
micvbang-0.0.14.dist-info/top_level.txt
test/__init__.py
test/test_progress.py
