Metadata-Version: 2.1
Name: micvbang
Version: 0.0.14
Summary: micvbang's often used utility functions
Home-page: https://github.com/micvbang/micvbang-python
Author: Michael Bang
Author-email: mic@vbang.dk
License: UNKNOWN
Platform: UNKNOWN
Classifier: Programming Language :: Python :: 3
